bailo/__init__.py
bailo/core/__init__.py
bailo/core/agent.py
bailo/core/client.py
bailo/core/enums.py
bailo/core/exceptions.py
bailo/core/utils.py
bailo/helper/__init__.py
bailo/helper/access_request.py
bailo/helper/datacard.py
bailo/helper/entry.py
bailo/helper/mirroredModel.py
bailo/helper/model.py
bailo/helper/release.py
bailo/helper/schema.py
bailo-3.4.0.dist-info/WHEEL
bailo-3.4.0.dist-info/METADATA
bailo-3.4.0.dist-info/RECORD
