Metadata-Version: 2.4
Name: bailo
Version: 3.4.0
Summary: Simplifies interacting with Bailo programmatically
Requires-Python: >=3.10
Classifier: Development Status :: 3 - Alpha
Classifier: Intended Audience :: Developers
Classifier: License :: OSI Approved :: MIT License
Classifier: Natural Language :: English
Classifier: Programming Language :: Python :: 3 :: Only
Classifier: Programming Language :: Python :: 3.10
Classifier: Programming Language :: Python :: 3.11
Classifier: Programming Language :: Python :: 3.12
Classifier: Programming Language :: Python :: 3.13
Classifier: Programming Language :: Python :: 3.14
Requires-Dist: requests==2.32.5
Requires-Dist: semantic-version==2.10.0
Requires-Dist: tqdm==4.67.1
Requires-Dist: mlflow-skinny[mlserver]==3.8.1 ; extra == "mlflow"
Requires-Dist: black==25.12.0 ; extra == "test"
Requires-Dist: check-manifest==0.51 ; extra == "test"
Requires-Dist: pre-commit==4.5.1 ; extra == "test"
Requires-Dist: pylint==4.0.4 ; extra == "test"
Requires-Dist: pylint_junit==0.3.5 ; extra == "test"
Requires-Dist: pytest-cov==7.0.0 ; extra == "test"
Requires-Dist: pytest-mock==3.15.1 ; extra == "test"
Requires-Dist: pytest-runner==6.0.1 ; extra == "test"
Requires-Dist: pytest==9.0.2 ; extra == "test"
Requires-Dist: pytest-github-actions-annotate-failures==0.3.0 ; extra == "test"
Requires-Dist: requests_mock==1.12.1 ; extra == "test"
Requires-Dist: shellcheck-py==0.11.0.1 ; extra == "test"
Requires-Dist: bailo[mlflow] ; extra == "test"
Project-URL: Changelog, https://github.com/gchq/Bailo/blob/main/lib/python/CHANGELOG.md
Project-URL: Documentation, https://github.com/gchq/bailo/tree/main#readme
Project-URL: Source, https://github.com/gchq/bailo
Project-URL: Tracker, https://github.com/gchq/bailo/issues
Provides-Extra: mlflow
Provides-Extra: test
